<?xml version="1.0" encoding="UTF-8"?>
<objects serializationModel="Studio.02.02.00">
	<object class="AudioFile" id="{6d0b1dcc-2db9-4dcd-90ad-66dedde457ab}">
		<property name="assetPath">
			<value>4du/glassWipe - Trimmed (3).wav</value>
		</property>
		<property name="frequencyInKHz">
			<value>48</value>
		</property>
		<property name="channelCount">
			<value>2</value>
		</property>
		<property name="length">
			<value>0.71997916666666661</value>
		</property>
		<relationship name="masterAssetFolder">
			<destination>{2e756c3c-c61b-4edd-8f86-b8abdd04a165}</destination>
		</relationship>
	</object>
</objects>
