<?xml version="1.0" encoding="UTF-8"?>
<objects serializationModel="Studio.02.02.00">
	<object class="AudioFile" id="{a0b78a58-821e-4cc8-a988-6e7fca0f9626}">
		<property name="assetPath">
			<value>ui-ish/SLR2.wav</value>
		</property>
		<property name="frequencyInKHz">
			<value>48</value>
		</property>
		<property name="channelCount">
			<value>1</value>
		</property>
		<property name="length">
			<value>0.40000000000000002</value>
		</property>
		<relationship name="masterAssetFolder">
			<destination>{2e756c3c-c61b-4edd-8f86-b8abdd04a165}</destination>
		</relationship>
	</object>
</objects>
