<?xml version="1.0" encoding="UTF-8"?>
<objects serializationModel="Studio.02.02.00">
	<object class="AudioFile" id="{aa6e6735-ab53-448f-ba53-e5365d35e0cc}">
		<property name="assetPath">
			<value>3du/dj-scratch-4 - Trimmed.wav</value>
		</property>
		<property name="frequencyInKHz">
			<value>48</value>
		</property>
		<property name="channelCount">
			<value>2</value>
		</property>
		<property name="length">
			<value>0.42597916666666669</value>
		</property>
		<relationship name="masterAssetFolder">
			<destination>{2e756c3c-c61b-4edd-8f86-b8abdd04a165}</destination>
		</relationship>
	</object>
</objects>
